openicl/__init__.py
openicl/icl_dataset_reader.py
openicl/icl_prompt_template.py
openicl/icl_evaluator/__init__.py
openicl/icl_evaluator/icl_acc_evaluator.py
openicl/icl_evaluator/icl_api_evaluator.py
openicl/icl_evaluator/icl_base_evaluator.py
openicl/icl_evaluator/icl_bleu_evaluator.py
openicl/icl_evaluator/icl_rouge_evaluator.py
openicl/icl_evaluator/icl_squad_evaluator.py
openicl/icl_inferencer/__init__.py
openicl/icl_inferencer/icl_base_inferencer.py
openicl/icl_inferencer/icl_channel_inferencer.py
openicl/icl_inferencer/icl_cot_inferencer.py
openicl/icl_inferencer/icl_gen_inferencer.py
openicl/icl_inferencer/icl_ppl_inferencer.py
openicl/icl_retriever/__init__.py
openicl/icl_retriever/icl_base_retriever.py
openicl/icl_retriever/icl_bm25_retriever.py
openicl/icl_retriever/icl_dpp_retriever.py
openicl/icl_retriever/icl_mdl_retriever.py
openicl/icl_retriever/icl_random_retriever.py
openicl/icl_retriever/icl_topk_retriever.py
openicl/icl_retriever/icl_votek_retriever.py
openicl/icl_retriever/icl_zero_retriever.py
openicl/utils/__init__.py
openicl/utils/api_service.py
openicl/utils/calculate.py
openicl/utils/check_type.py
openicl/utils/collators.py
openicl/utils/icl_common_utils.py
openicl/utils/logging.py
openicl-0.1.8.dist-info/LICENSE
openicl-0.1.8.dist-info/METADATA
openicl-0.1.8.dist-info/WHEEL
openicl-0.1.8.dist-info/top_level.txt
openicl-0.1.8.dist-info/RECORD
