Metadata-Version: 2.1
Name: openicl
Version: 0.1.8
Summary: An open source framework for in-context learning.
Home-page: https://github.com/Shark-NLP/OpenICL
Author: Zhenyu Wu, Yaoxiang Wang, Zhiyong Wu, Jiacheng Ye
Keywords: AI,NLP,in-context learning
Classifier: Programming Language :: Python :: 3.8
Classifier: Programming Language :: Python :: 3.9
Classifier: Programming Language :: Python :: 3.10
Classifier: Intended Audience :: Developers
Classifier: Intended Audience :: Education
Classifier: Intended Audience :: Science/Research
Requires-Python: >=3.8.0
License-File: LICENSE
Requires-Dist: transformers (==4.28.1)
Requires-Dist: tokenizers (==0.13.3)
Requires-Dist: accelerate
Requires-Dist: datasets (>=2.7.1)
Requires-Dist: evaluate (>=0.3.0)
Requires-Dist: faiss-gpu (>=1.7.2)
Requires-Dist: nltk (>=3.8)
Requires-Dist: numpy (>=1.23.4)
Requires-Dist: openai (>=0.27.1)
Requires-Dist: rank-bm25 (>=0.2.2)
Requires-Dist: requests (>=2.28.1)
Requires-Dist: scikit-learn (>=1.2.1)
Requires-Dist: sentence-transformers (>=2.2.2)
Requires-Dist: torch (>=1.13.1)
Requires-Dist: tqdm (>=4.64.1)
